{
  "generatedMT": "2026-06-25T17:02:30.430880-06:00",
  "ts": "17:02 MT",
  "mlbLive": [
    {
      "id": "401815898",
      "sport": "MLB",
      "home": "DET",
      "away": "HOU",
      "homeScore": "0",
      "awayScore": "0",
      "state": "in",
      "period": 2,
      "displayClock": "0:00",
      "venue": "Comerica Park",
      "date": "2026-06-25T22:40Z",
      "network": "MLB.TV",
      "homeML": null,
      "awayML": null,
      "ou": null,
      "spread": null,
      "provider": ""
    },
    {
      "id": "401815901",
      "sport": "MLB",
      "home": "WSH",
      "away": "PHI",
      "homeScore": "0",
      "awayScore": "0",
      "state": "in",
      "period": 1,
      "displayClock": "0:00",
      "venue": "Nationals Park",
      "date": "2026-06-25T22:45Z",
      "network": "MLB.TV",
      "homeML": null,
      "awayML": null,
      "ou": null,
      "spread": null,
      "provider": ""
    }
  ],
  "nbaLive": [],
  "nhlLive": [],
  "tennisLive": [],
  "mlbAll": [
    {
      "id": "401815899",
      "sport": "MLB",
      "home": "TB",
      "away": "KC",
      "homeScore": "13",
      "awayScore": "2",
      "state": "post",
      "period": 9,
      "displayClock": "0:00",
      "venue": "Tropicana Field",
      "date": "2026-06-25T16:10Z",
      "network": "MLB.TV",
      "homeML": null,
      "awayML": null,
      "ou": null,
      "spread": null,
      "provider": ""
    },
    {
      "id": "401815902",
      "sport": "MLB",
      "home": "PIT",
      "away": "SEA",
      "homeScore": "5",
      "awayScore": "1",
      "state": "post",
      "period": 9,
      "displayClock": "0:00",
      "venue": "PNC Park",
      "date": "2026-06-25T16:35Z",
      "network": "MLB.TV",
      "homeML": null,
      "awayML": null,
      "ou": null,
      "spread": null,
      "provider": ""
    },
    {
      "id": "401815905",
      "sport": "MLB",
      "home": "SF",
      "away": "ATH",
      "homeScore": "6",
      "awayScore": "9",
      "state": "post",
      "period": 9,
      "displayClock": "0:00",
      "venue": "Oracle Park",
      "date": "2026-06-25T19:45Z",
      "network": "MLB.TV",
      "homeML": null,
      "awayML": null,
      "ou": null,
      "spread": null,
      "provider": ""
    },
    {
      "id": "401815898",
      "sport": "MLB",
      "home": "DET",
      "away": "HOU",
      "homeScore": "0",
      "awayScore": "0",
      "state": "in",
      "period": 2,
      "displayClock": "0:00",
      "venue": "Comerica Park",
      "date": "2026-06-25T22:40Z",
      "network": "MLB.TV",
      "homeML": null,
      "awayML": null,
      "ou": null,
      "spread": null,
      "provider": ""
    },
    {
      "id": "401815901",
      "sport": "MLB",
      "home": "WSH",
      "away": "PHI",
      "homeScore": "0",
      "awayScore": "0",
      "state": "in",
      "period": 1,
      "displayClock": "0:00",
      "venue": "Nationals Park",
      "date": "2026-06-25T22:45Z",
      "network": "MLB.TV",
      "homeML": null,
      "awayML": null,
      "ou": null,
      "spread": null,
      "provider": ""
    },
    {
      "id": "401815903",
      "sport": "MLB",
      "home": "TOR",
      "away": "TEX",
      "homeScore": null,
      "awayScore": null,
      "state": "pre",
      "period": 1,
      "displayClock": "0:00",
      "venue": "Rogers Centre",
      "date": "2026-06-25T23:07Z",
      "network": "MLB.TV",
      "homeML": null,
      "awayML": null,
      "ou": 8.0,
      "spread": -1.5,
      "provider": "DraftKings"
    },
    {
      "id": "401815897",
      "sport": "MLB",
      "home": "NYM",
      "away": "CHC",
      "homeScore": null,
      "awayScore": null,
      "state": "pre",
      "period": 1,
      "displayClock": "0:00",
      "venue": "Citi Field",
      "date": "2026-06-25T23:10Z",
      "network": "MLB.TV",
      "homeML": null,
      "awayML": null,
      "ou": 8.5,
      "spread": 1.5,
      "provider": "DraftKings"
    },
    {
      "id": "401815900",
      "sport": "MLB",
      "home": "BOS",
      "away": "NYY",
      "homeScore": null,
      "awayScore": null,
      "state": "pre",
      "period": 1,
      "displayClock": "0:00",
      "venue": "Fenway Park",
      "date": "2026-06-25T23:10Z",
      "network": "MLB.TV",
      "homeML": null,
      "awayML": null,
      "ou": 8.0,
      "spread": 1.5,
      "provider": "DraftKings"
    },
    {
      "id": "401815904",
      "sport": "MLB",
      "home": "STL",
      "away": "ARI",
      "homeScore": null,
      "awayScore": null,
      "state": "pre",
      "period": 1,
      "displayClock": "0:00",
      "venue": "Busch Stadium",
      "date": "2026-06-25T23:45Z",
      "network": "ESPN Unlmtd",
      "homeML": null,
      "awayML": null,
      "ou": 9.0,
      "spread": -1.5,
      "provider": "DraftKings"
    }
  ],
  "nbaAll": [],
  "nhlAll": [],
  "liveProbs": {
    "mlb": [
      {
        "homeWinProb": 0.5,
        "awayWinProb": 0.5,
        "hScore": 0,
        "aScore": 0,
        "gameId": "401815898",
        "home": "DET",
        "away": "HOU",
        "state": "in"
      },
      {
        "homeWinProb": 0.5,
        "awayWinProb": 0.5,
        "hScore": 0,
        "aScore": 0,
        "gameId": "401815901",
        "home": "WSH",
        "away": "PHI",
        "state": "in"
      }
    ],
    "nba": [],
    "nhl": []
  },
  "autoSettled": []
}