{
  "x_post": "Midday read \u2014 07/14\nTop edge holding: AL @ NL \u2192 NL ML -110 | 5400% model / 0% market | EV D",
  "x_thread": [
    "Midday check \u2014 July 14, 2026\n\n1 MLB",
    "No results yet \u2014 games begin this afternoon/evening.\n\nModel is watching for any line movement that closes the gap on flagged edges.",
    "Model still tracking:\nAL @ NL \u2192 NL ML -110\nModel: 5400.0% | Market: 0.0% | Edge: +0.0% | EV D\n\nLine movement direction: model edge narrowing \u2014 watch closing line.",
    "Pre-game post at 4:45 PM MT \u2014 final model reads before tonight's slate. Accountability recap at 10 PM."
  ],
  "instagram_caption": "Midday model check for July 14, 2026. 1 MLB on today's card. Top edge remains: AL @ NL \u2192 NL ML -110, model at 5400.0% against market implied \u2014 EV D. Pre-game final read drops at 4:45 PM.",
  "instagram_hashtags": [
    "SportsBetting",
    "SportsAnalytics",
    "ModelOutput",
    "DataDriven",
    "ExpectedValue"
  ],
  "story_bullets": [
    "Top edge: EV D (+0%)",
    "1 MLB",
    "Pre-game post: 4:45 PM Mountain"
  ],
  "content_theme": "midday_adjustment",
  "highlight_game": "AL @ NL",
  "generated_at": "2026-07-14 15:51 MT",
  "slot": "2pm",
  "slot_label": "Midday Adjustments"
}