{
  "x_post": "Morning model \u2014 07/22 | 17 MLB\nTop edge: LAD @ PHI \u2192 LAD ML -165 | 6620% model / 0% market / +0.0% edge | EV D",
  "x_thread": [
    "Morning model sweep \u2014 July 22, 2026\n\n17 MLB\n\n0 edges flagged above market implied \u2193",
    "Top read: LAD @ PHI \u2192 LAD ML -165\nModel: 6620.0% | Market: 0.0% | Edge: +0.0% | EV D\n55",
    "Weather factor \u2014 NYY: 13 mph, 86\u00b0F\n\nWind direction and speed affect outdoor totals. Model accounts for park + conditions in O/U projections.",
    "Playoff context:\n\n\u2022 PIT @ NYY \u2014 Doubleheader - Game 1\n\u2022 BAL @ BOS \u2014 Doubleheader - Game 1 \u2013 Makeup from July 21\n\u2022 PIT @ NYY \u2014 Doubleheader - Game 2 - Makeup from July 21\n\u2022 BAL @ BOS \u2014 Doubleheader - Game 2\n\nNext: Midday adjustments at 2 PM MT."
  ],
  "instagram_caption": "Morning model sweep for July 22, 2026. 17 MLB across professional sports \u2014 the engine flagged 0 edges above market implied. Top read: LAD @ PHI \u2192 LAD ML -165, where the model projects 6620.0% probability against a market-implied 0.0%, a +0.0% edge rated EV D. All projections update with line movement throughout the day.",
  "instagram_hashtags": [
    "SportsBetting",
    "SportsAnalytics",
    "ModelOutput",
    "DataDriven",
    "ExpectedValue"
  ],
  "story_bullets": [
    "Top edge: LAD @ PHI +0%",
    "17 MLB",
    "Wind alert: 13 mph at NYY"
  ],
  "content_theme": "morning_preview",
  "highlight_game": "LAD @ PHI",
  "generated_at": "2026-07-22 10:31 MT",
  "slot": "10am",
  "slot_label": "Morning Preview"
}